codestare/mazes/__init__.py
codestare/mazes/algorithms.py
codestare/mazes/main.py
codestare/mazes/representation.py
codestare_maze-0.1.2.dist-info/LICENSE.rst
codestare_maze-0.1.2.dist-info/METADATA
codestare_maze-0.1.2.dist-info/WHEEL
codestare_maze-0.1.2.dist-info/entry_points.txt
codestare_maze-0.1.2.dist-info/top_level.txt
codestare_maze-0.1.2.dist-info/RECORD
