Metadata-Version: 2.1
Name: codestare-maze
Version: 0.1.2
Summary: Simple Maze Generator
Home-page: https://themenwhostareatco.de/
Author: Maximilian Schmidt
Author-email: ga97lul@mytum.de
Keywords: maze,dnd,rpg
Classifier: Programming Language :: Python :: 3
Requires-Python: >=3.9
License-File: LICENSE.rst
Provides-Extra: dev
Requires-Dist: setuptools-changelog (==1.0.0) ; extra == 'dev'
Provides-Extra: test
Requires-Dist: pytest (==7.1.2) ; extra == 'test'
